{
  "bl": [
    {
      "breachdmg": 7.9,
      "breachmax": 0.8,
      "breachmin": 0.4,
      "class": 1,
      "cost": 37430,
      "damage": 9.8,
      "damagedist": {
        "T": 1
      },
      "distdraw": 1.94,
      "edID": 128049428,
      "eddbID": 841,
      "falloff": 600,
      "grp": "bl",
      "id": "10",
      "integrity": 40,
      "mass": 2,
      "mount": "F",
      "piercing": 18,
      "power": 0.62,
      "range": 3000,
      "rating": "E",
      "thermload": 3.5,
      "symbol": "Hpt_BeamLaser_Fixed_Small"
    },
    {
      "breachdmg": 6.1,
      "breachmax": 0.8,
      "breachmin": 0.4,
      "class": 1,
      "cost": 74650,
      "damage": 7.66,
      "damagedist": {
        "T": 1
      },
      "distdraw": 2.11,
      "edID": 128049432,
      "eddbID": 844,
      "falloff": 600,
      "grp": "bl",
      "id": "0p",
      "integrity": 40,
      "mass": 2,
      "mount": "G",
      "piercing": 18,
      "power": 0.6,
      "range": 3000,
      "rating": "E",
      "thermload": 3.6,
      "symbol": "Hpt_BeamLaser_Gimbal_Small"
    },
    {
      "breachdmg": 4.3,
      "breachmax": 0.8,
      "breachmin": 0.4,
      "class": 1,
      "cost": 500000,
      "damage": 5.4,
      "damagedist": {
        "T": 1
      },
      "distdraw": 1.32,
      "edID": 128049435,
      "eddbID": 847,
      "falloff": 600,
      "eps": 1.32,
      "grp": "bl",
      "hps": 2.4,
      "id": "0q",
      "integrity": 40,
      "mass": 2,
      "mount": "T",
      "piercing": 18,
      "power": 0.57,
      "range": 3000,
      "rating": "F",
      "thermload": 2.4,
      "symbol": "Hpt_BeamLaser_Turret_Small"
    },
    {
      "breachdmg": 3.9,
      "breachmax": 0.8,
      "breachmin": 0.4,
      "class": 1,
      "cost": 56150,
      "damage": 4.9,
      "damagedist": {
        "T": 1
      },
      "distdraw": 2.52,
      "edID": 128671346,
      "eddbID": 1476,
      "falloff": 600,
      "grp": "bl",
      "id": "b0",
      "integrity": 40,
      "mass": 2,
      "mount": "F",
      "name": "Retributor",
      "piercing": 18,
      "power": 0.62,
      "pp": "Edmund Mahon",
      "range": 3000,
      "rating": "E",
      "thermload": 2.7,
      "symbol": "Hpt_BeamLaser_Fixed_Small_Heat"
    },
    {
      "breachdmg": 12.8,
      "breachmax": 0.8,
      "breachmin": 0.4,
      "class": 2,
      "cost": 299520,
      "damage": 15.96,
      "damagedist": {
        "T": 1
      },
      "distdraw": 3.16,
      "edID": 128049429,
      "eddbID": 842,
      "falloff": 600,
      "grp": "bl",
      "id": "0r",
      "integrity": 51,
      "mass": 4,
      "mount": "F",
      "piercing": 35,
      "power": 1.01,
      "range": 3000,
      "rating": "D",
      "thermload": 5.1,
      "symbol": "Hpt_BeamLaser_Fixed_Medium"
    },
    {
      "breachdmg": 10,
      "breachmax": 0.8,
      "breachmin": 0.4,
      "class": 2,
      "cost": 500600,
      "damage": 12.52,
      "damagedist": {
        "T": 1
      },
      "distdraw": 3.44,
      "edID": 128049433,
      "eddbID": 845,
      "falloff": 600,
      "grp": "bl",
      "id": "0s",
      "integrity": 51,
      "mass": 4,
      "mount": "G",
      "piercing": 35,
      "power": 1,
      "range": 3000,
      "rating": "D",
      "thermload": 5.3,
      "symbol": "Hpt_BeamLaser_Gimbal_Medium"
    },
    {
      "breachdmg": 7.1,
      "breachmax": 0.8,
      "breachmin": 0.4,
      "class": 2,
      "cost": 2099900,
      "damage": 8.82,
      "damagedist": {
        "T": 1
      },
      "distdraw": 2.16,
      "edID": 128049436,
      "eddbID": 848,
      "falloff": 600,
      "grp": "bl",
      "id": "0t",
      "integrity": 51,
      "mass": 4,
      "mount": "T",
      "piercing": 35,
      "power": 0.93,
      "range": 3000,
      "rating": "E",
      "thermload": 3.5,
      "symbol": "Hpt_BeamLaser_Turret_Medium"
    },
    {
      "breachdmg": 20.6,
      "breachmax": 0.8,
      "breachmin": 0.4,
      "class": 3,
      "cost": 1177600,
      "damage": 25.78,
      "damagedist": {
        "T": 1
      },
      "distdraw": 5.1,
      "edID": 128049430,
      "eddbID": 843,
      "falloff": 600,
      "grp": "bl",
      "id": "0u",
      "integrity": 64,
      "mass": 8,
      "mount": "F",
      "piercing": 50,
      "power": 1.62,
      "range": 3000,
      "rating": "C",
      "thermload": 7.2,
      "symbol": "Hpt_BeamLaser_Fixed_Large"
    },
    {
      "breachdmg": 16.2,
      "breachmax": 0.8,
      "breachmin": 0.4,
      "class": 3,
      "cost": 2396160,
      "damage": 20.28,
      "damagedist": {
        "T": 1
      },
      "distdraw": 5.58,
      "edID": 128049434,
      "eddbID": 846,
      "falloff": 600,
      "grp": "bl",
      "id": "0v",
      "integrity": 64,
      "mass": 8,
      "mount": "G",
      "piercing": 50,
      "power": 1.6,
      "range": 3000,
      "rating": "C",
      "thermload": 7.6,
      "symbol": "Hpt_BeamLaser_Gimbal_Large"
    },
    {
      "breachdmg": 11.5,
      "breachmax": 0.8,
      "breachmin": 0.4,
      "class": 3,
      "cost": 19399600,
      "damage": 14.34,
      "damagedist": {
        "T": 1
      },
      "distdraw": 3.51,
      "edID": 128049437,
      "eddbID": 849,
      "falloff": 600,
      "grp": "bl",
      "id": "0o",
      "integrity": 64,
      "mass": 8,
      "mount": "T",
      "piercing": 50,
      "power": 1.51,
      "range": 3000,
      "rating": "D",
      "thermload": 5.1,
      "symbol": "Hpt_BeamLaser_Turret_Large"
    },
    {
      "breachdmg": 33.1,
      "breachmax": 0.8,
      "breachmin": 0.4,
      "class": 4,
      "cost": 2396160,
      "damage": 41.38,
      "damagedist": {
        "T": 1
      },
      "distdraw": 8.19,
      "edID": 128049431,
      "eddbID": 1540,
      "falloff": 600,
      "grp": "bl",
      "id": "0w",
      "integrity": 80,
      "mass": 16,
      "mount": "F",
      "piercing": 60,
      "power": 2.61,
      "range": 3000,
      "rating": "A",
      "thermload": 9.9,
      "symbol": "Hpt_BeamLaser_Fixed_Huge"
    },
    {
      "breachdmg": 26.1,
      "breachmax": 0.8,
      "breachmin": 0.4,
      "class": 4,
      "cost": 8746160,
      "damage": 32.68,
      "damagedist": {
        "T": 1
      },
      "distdraw": 8.99,
      "edID": 128681994,
      "eddbID": 1544,
      "falloff": 600,
      "grp": "bl",
      "id": "0x",
      "integrity": 80,
      "mass": 16,
      "mount": "G",
      "piercing": 60,
      "power": 2.57,
      "range": 3000,
      "rating": "A",
      "thermload": 10.6,
      "symbol": "Hpt_BeamLaser_Gimbal_Huge"
    }
  ]
}
